<annotation>
	<folder>JPEGImages</folder>
	<filename>IMG_0095.jpeg</filename>
	<path>C:\cygwin64\home\jaswa\Capstone\test\test\SmartGym\keras-yolo3\VOCdevkit\VOC2007\JPEGImages\IMG_0095.jpeg</path>
	<source>
		<database>Unknown</database>
	</source>
	<size>
		<width>640</width>
		<height>480</height>
		<depth>3</depth>
	</size>
	<segmented>0</segmented>
	<object>
		<name>weights</name>
		<pose>Unspecified</pose>
		<truncated>1</truncated>
		<difficult>0</difficult>
		<bndbox>
			<xmin>324</xmin>
			<ymin>296</ymin>
			<xmax>612</xmax>
			<ymax>480</ymax>
		</bndbox>
	</object>
	<object>
		<name>weights</name>
		<pose>Unspecified</pose>
		<truncated>1</truncated>
		<difficult>0</difficult>
		<bndbox>
			<xmin>213</xmin>
			<ymin>1</ymin>
			<xmax>421</xmax>
			<ymax>167</ymax>
		</bndbox>
	</object>
	<object>
		<name>weights</name>
		<pose>Unspecified</pose>
		<truncated>0</truncated>
		<difficult>0</difficult>
		<bndbox>
			<xmin>237</xmin>
			<ymin>277</ymin>
			<xmax>337</xmax>
			<ymax>378</ymax>
		</bndbox>
	</object>
</annotation>
